storage_interfaces/__init__.py
storage_interfaces/__version__.py
storage_interfaces/_compat.py
storage_interfaces/abstracts.py
storage_interfaces/scsi/__init__.py
storage_interfaces/scsi/abstracts.py
storage_interfaces-1.0.5.dist-info/AUTHORS
storage_interfaces-1.0.5.dist-info/LICENSE
storage_interfaces-1.0.5.dist-info/METADATA
storage_interfaces-1.0.5.dist-info/WHEEL
storage_interfaces-1.0.5.dist-info/pbr.json
storage_interfaces-1.0.5.dist-info/top_level.txt
storage_interfaces-1.0.5.dist-info/RECORD
