Metadata-Version: 2.1
Name: storage-interfaces
Version: 1.0.5
Summary: Abstract classes for representing storage-related objects
Home-page: https://github.com/Infinidat/storage_interfaces
Author: Infinidat Ltd.
Author-email: info@infinidat.com
License: BSD3
Platform: UNKNOWN
Classifier: Programming Language :: Python :: 3.5
Classifier: Programming Language :: Python :: 3.6
Classifier: Programming Language :: Python :: 3.7
Classifier: Programming Language :: Python :: 3.8
Requires-Python: >=3.5
Provides-Extra: testing
Requires-Dist: astroid (>=2.0) ; extra == 'testing'
Requires-Dist: pylint (~=2.3.1) ; extra == 'testing'
Requires-Dist: pytest ; extra == 'testing'
